Workbook

Sheet TEMP

Sheet HISTORICAL INFORMATION
A1: ACUTAAS CHEMICALS LIMITED
A2: HISTORICAL FINANCIAL INFORMATION
A4: INCOME STATEMENT | H4: 2021 | I4: =H4+1 -> 2022 | J4: =I4+1 -> 2023 | K4: =J4+1 -> 2024 | L4: =K4+1 -> 2025 | M4: =L4+1 -> 2026 | N4: =M4+1 -> 2027 | O4: =N4+1 -> 2028 | P4: =O4+1 -> 2029 | ... R4: =Q4+1 -> 2031
D5: Income
D6: Revenue from operations | H6: 34060.79 | I6: 52013.5 | J6: 61673.45 | K6: 71747.45 | L6: 100687.55
D7: Other Income | H7: 137.97 | I7: 276.23 | J7: 431.98 | K7: 749.09 | L7: 1692.94
D8: Total Income | H8: 34198.76 | I8: 52289.73 | J8: 62105.43 | K8: 72496.54 | L8: 102380.49
D9: Expenses
D10: Cost of materials consumed | H10: 17487.2 | I10: 28233.3 | J10: 34585.12 | K10: 44017.16 | L10: 56981.13
D11: Changes in inventories of finished goods, stock in trade and work in progress | H11: 481.36 | I11: -949.67 | J11: -1495.59 | K11: -2848.34 | L11: -1762.96
D12: Employee benefits expense | H12: 2100.76 | I12: 4136.64 | J12: 4883.61 | K12: 6311.44 | L12: 8365.59
D13: Finance costs | H13: 561.84 | I13: 640.73 | J13: 241.23 | K13: 594.03 | L13: 621.84
D14: Depreciation and amortization expense | H14: 418.81 | I14: 1008.02 | J14: 1234.24 | K14: 1605.52 | L14: 2662.14
D15: Other expenses | H15: 5976.17 | I15: 10075.67 | J15: 11439.64 | K15: 11418.21 | L15: 13896.45
D16: Total expenses | H16: 27026.14 | I16: 43144.69 | J16: 50888.25 | K16: 61098.02 | L16: 80764.19
D17: Profit before exceptional items and tax | H17: 7172.62 | I17: 9145.04 | J17: 11217.18 | K17: 11398.52 | L17: 21616.3
D18: Exceptional items | H18: 0 | I18: 0 | J18: 0 | K18: -3208.39 | L18: 0
D19: Profit before tax | H19: =H17 -> 7172.62 | I19: =I17 -> 9145.04 | J19: 11217.18 | K19: 8190.13 | L19: 21616.3
D20: Tax expense
D21: Current tax | H21: 1756.4 | I21: 1672.15 | J21: 2637.72 | K21: 2901.53 | L21: 4918.95
D22: Deferred tax | H22: 16.33 | I22: 278.28 | J22: 250.49 | K22: 417.8 | L22: 655.58
D23: Total tax expense | H23: 1772.73 | I23: 1950.43 | J23: 2888.21 | K23: 3319.33 | L23: 5574.53
D24: Profit after tax | H24: 5399.89 | I24: 7194.61 | J24: 8328.97 | K24: 4870.8 | L24: 16041.77
D25: Other comprehensive income (OCI)
D26: Items that will not be reclassified to profit or loss
D27: Remeasurement of defined employee benefit plans | H27: -3.73 | I27: 80.65 | J27: 16.83 | K27: -6.67 | L27: -17.48
D28: Tax impact on items that will not be reclassified to of profit or loss | H28: 0.94 | I28: -20.3 | J28: 0 | K28: 1.68 | L28: 3.67
D29: Exchange differences on translation of financial statements of foreign exchange | H29: -85.18 | I29: 128.79 | J29: 290.36 | K29: -717.37 | L29: 0
D30: Other comprehensive income, net of tax | H30: =H27+H28+H29 -> -87.97 | I30: =I27+I28+I29 -> 189.14 | J30: 307.19 | K30: -722.36 | L30: -13.81
D31: Total comprehensive income for the year | H31: 5311.92 | I31: 7383.75 | J31: 8636.16 | K31: 4148.44 | L31: 16027.96
D32: Profit attributal to
D33: Owners of the company | H33: 0 | I33: 0 | J33: 0 | K33: 4277.3 | L33: 15871.36
D34: Non - controlling interest | H34: 0 | I34: 0 | J34: 0 | K34: 593.5 | L34: 170.41
D35: Other comprehensive income attributal to
D36: Owners of the company | H36: 0 | I36: 0 | J36: 0 | K36: -724.27 | L36: -12.51
D37: Non - controlling interest | H37: 0 | I37: 0 | J37: 0 | K37: 1.91 | L37: -1.3
D38: Earnings per equity share (Face value of ₹5 each)
D39: Basic (₹) | H39: 17.14 | I39: 21.03 | J39: 11.43 | K39: 5.83 | L39: 19.81
D40: Diluted (₹) | H40: 17.14 | I40: 21.03 | J40: 11.43 | K40: 5.83 | L40: 19.81
D41: Nominal value of equity shares | H41: 10 | I41: 10
A46: BALANCE SHEET | H46: 2021 | I46: =H46+1 -> 2022 | J46: =I46+1 -> 2023 | K46: =J46+1 -> 2024 | L46: =K46+1 -> 2025 | M46: =L46+1 -> 2026 | N46: =M46+1 -> 2027 | O46: =N46+1 -> 2028 | P46: =O46+1 -> 2029 | Q46: =P46+1 -> 2030
D47: ASSETS
D48: Non-current assets
D49: Property, plant and equipment | H49: 14217.62 | I49: 15844.31 | J49: 18435.38 | K49: 32290.32 | L49: 46292.28
D50: Capital work-in-progress | H50: 1842.91 | I50: 189.16 | J50: 2551.76 | K50: 12542.32 | L50: 13028.4
D51: Right-of-use assets | H51: 20.01 | I51: 1936.57 | J51: 3741.91 | K51: 3715.21 | L51: 4239.03
D52: Goodwill | H52: 2570.11 | I52: 1859.56 | J52: 2032.29 | K52: 5680.09 | L52: 5680.09
D53: Intangible assets | H53: 0 | I53: 813.05 | J53: 1685.74 | K53: 1030.5 | L53: 827.51
D54: Intangible assets under development | H54: 0 | I54: 106.89 | J54: 427.78 | K54: 0 | L54: 0
D55: Financial Assets | H55: 0
D56: Investments | H56: 142.86 | I56: 171.31 | J56: 165.07 | K56: 19.53 | L56: 19.53
D57: Loans | H57: 0 | I57: 0 | J57: 22.06
D58: Other financial assets | H58: 270.6 | I58: 1085.73 | J58: 624.11 | K58: 257.72 | L58: 493.24
D59: Income tax assets (net) | H59: 0 | I59: 0 | J59: 0 | K59: 250.97 | L59: 15.31
D60: Other non-current assets | H60: 639.58 | I60: 924.57 | J60: 1294.85 | K60: 4473.31 | L60: 5167.12
D61: Total non-current assets | H61: 19703.69 | I61: 22931.15 | J61: 30980.95 | K61: 60259.97 | L61: 75762.51
D62: Current assets
D63: Inventories | H63: 6036.31 | I63: 11217.09 | J63: 11917.3 | K63: 15673.41 | L63: 17994.02
D64: Financial assets
D65: i) Trade receivables | H65: 12069.09 | I65: 16370.22 | J65: 23026.11 | K65: 20635.21 | L65: 29049.47
D66: ii) Cash and cash equivalents | H66: 268.46 | I66: 1029.66 | J66: 3053.26 | K66: 2970.44 | L66: 18522.43
D67: iii) Bank balances other than cash and cash equivalents | H67: 0 | I67: 8925.49 | J67: 2813.76 | K67: 2360.75 | L67: 6370.4
D68: iv) Loans | H68: 33.43 | I68: 65.39 | J68: 133.58 | K68: 155.06 | L68: 215.98
D69: v) Current Tax Assets (Net) | H69: 0 | I69: 494.06 | J69: 322.09 | K69: 0 | L69: 0
D70: Other current assets | H70: 3215.83 | I70: 4855.23 | J70: 4446.79 | K70: 7535.49 | L70: 7011.3
D71: Total current assets | H71: 21623.12 | I71: 42957.14 | J71: 45712.89 | K71: 49330.36 | L71: 79163.6
D72: Total assets | H72: 41326.81 | I72: 65888.29 | J72: 76693.84 | K72: 109590.33 | L72: 154926.11
D73: EQUITY AND LIABILITIES
D74: Equity
D75: Equity share capital | H75: 3150 | I75: 3643.71 | J75: 3643.71 | K75: 3688.06 | L75: 4093.45
D76: Other equity | H76: 13543.32 | I76: 48583.69 | J76: 55752.21 | K76: 63711.68 | L76: 126869.42
D77: Equity attributable to owners of the Company | H77: =H76+H75 -> 16693.32 | I77: =I76+I75 -> 52227.4 | J77: =J76+J75 -> 59395.92 | K77: 67399.74 | L77: 130962.87
D78: Non controlling interests | H78: 0 | I78: 0 | J78: 0 | K78: 876.06 | L78: 1045.17
D79: Total equity | H79: 16693.32 | I79: 52227.4 | J79: 59395.92 | K79: 68275.8 | L79: 132008.04
D80: Non-current liabilities
D81: Financial liabilities
D82: i) Borrowings | H82: 7264.42 | I82: 58.81 | J82: 62.59 | K82: 11364.12 | L82: 0
D83: ii) Lease liabilities | H83: 0 | I83: 0 | J83: 0 | K83: 0 | L83: 475.44
D84: Provisions | H84: 436.84 | I84: 43.6 | J84: 68.14 | K84: 131.6 | L84: 254.64
D85: Deferred tax liabilities (net) | H85: 327.85 | I85: 626.43 | J85: 882.58 | K85: 1301.8 | L85: 1963.25
D86: Total non-current liabilities | H86: 8029.11 | I86: 728.84 | J86: 1013.31 | K86: 12797.52 | L86: 2693.33
D87: Current liabilities
D88: Financial liabilities
D89: i) Borrowings | H89: 6399.15 | I89: 25.6 | J89: 297.44 | K89: 10300.54 | L89: 818.43
D90: ii) Trade payables
D91: a) Total outstanding dues of micro enterprises and small enterprises | H91: 39.04 | I91: 1508.05 | J91: 7651.11 | K91: 2135.47 | L91: 5432.27
D92: b) Total outstanding dues of other than micro enterprises and small enterprises | H92: 8438.46 | I92: 10333.71 | J92: 6553.66 | K92: 11325.41 | L92: 10172.3
D93: Other current liabilities | H93: 1515.97 | I93: 462.64 | J93: 643.39 | K93: 3435.99 | L93: 1347.74
D94: Provisions | H94: 96.62 | I94: 602.05 | J94: 1139.01 | K94: 1319.6 | L94: 2454
D95: Current Tax Liability (Net) | H95: 115.16 | I95: 0 | J95: 0 | K95: 0 | L95: 0
D96: Total current liabilities | H96: 16604.4 | I96: 12932.05 | J96: 16284.61 | K96: 28517.01 | L96: 20224.74
D97: Total liabilities | H97: 24633.5 | I97: 13660.89 | J97: 17297.92 | K97: 41314.53 | L97: 22918.07
D98: Total equity and liabilities | H98: 41326.81 | I98: 65888.29 | J98: 76693.84 | K98: 109590.33 | L98: 154926.11
A104: CASHFLOW STATEMENT | H104: 2021 | I104: =H104+1 -> 2022 | J104: =I104+1 -> 2023 | K104: =J104+1 -> 2024 | L104: =K104+1 -> 2025 | M104: =L104+1 -> 2026 | N104: =M104+1 -> 2027 | O104: =N104+1 -> 2028 | P104: =O104+1 -> 2029 | Q104: =P104+1 -> 2030
D105: CASH FLOWS FROM OPERATING ACTIVITIES
D106: Profit before Tax | H106: 7172.62 | I106: 9145.04 | J106: 11217.18 | K106: 8190.13 | L106: 21616.3
D107: Adjustments for:
D108: Depreciation and amortisation | H108: 418.8 | I108: 1008.02 | J108: 1234.24 | K108: 1605.52 | L108: 2662.14
D109: (Gain)/Loss on disposal of property, plant and equipment | H109: 1.78 | I109: - | J109: 74.66 | K109: -20.84 | L109: -1.43
D110: Bad debts, provision for trade receivables and advances | H110: 0 | I110: 0 | J110: 0 | K110: 0 | L110: 208.71
...

Sheet MODEL
A1: ='HISTORICAL INFORMATION'!A1 -> ACUTAAS CHEMICALS LIMITED | J1: HISTORICAL PERIOD | M1: FORECAST PERIOD
A2: FINANCIAL STATEMENTS & DCF ANALYSIS | H2: ='HISTORICAL INFORMATION'!H4 -> 2021 | I2: ='HISTORICAL INFORMATION'!I4 -> 2022 | J2: ='HISTORICAL INFORMATION'!J4 -> 2023 | K2: ='HISTORICAL INFORMATION'!K4 -> 2024 | L2: ='HISTORICAL INFORMATION'!L4 -> 2025 | M2: ='HISTORICAL INFORMATION'!M4 -> 2026 | N2: ='HISTORICAL INFORMATION'!N4 -> 2027 | O2: ='HISTORICAL INFORMATION'!O4 -> 2028 | ... R2: ='HISTORICAL INFORMATION'!R4 -> 2031
D3: Master check | H3: =IF(H74<1,"OK",IF(H74>1,"ERROR")) -> OK | I3: =IF(I74<1,"OK",IF(I74>1,"ERROR")) -> OK | J3: =IF(J74<1,"OK",IF(J74>1,"ERROR")) -> OK | K3: =IF(K74<1,"OK",IF(K74>1,"ERROR")) -> OK | L3: =IF(L74<1,"OK",IF(L74>1,"ERROR")) -> OK | M3: =IF(M74<1,"OK",IF(M74>1,"ERROR")) -> OK | N3: =IF(N74<1,"OK",IF(N74>1,"ERROR")) -> OK | O3: =IF(O74<1,"OK",IF(O74>1,"ERROR")) -> OK | ... R3: =IF(R74<1,"OK",IF(R74>1,"ERROR")) -> OK
A5: RATIO & ASSUMPTIONS
D7: LIVE SCENARIO | E7: Base Case | F7: Units | G7: =IF(E7=SCENARIOS!D5,1,IF(MODEL!E7=SCENARIOS!D6,2,3)) -> 1
D8: Revenue growth | F8: % | H8: - | I8: =I25/H25-1 -> 0.5270785 | J8: =J25/I25-1 -> 0.18572005 | K8: =K25/J25-1 -> 0.16334419 | L8: =L25/K25-1 -> 0.40336068 | M8: {=CHOOSE(G7,SCENARIOS!H5:M5,SCENARIOS!H6:M6,SCENARIOS!H7:M7)} -> 0.31987586 | N8: 0.28788827 | O8: 0.25909944 | P8: 0.2331895 | Q8: 0.20987055 | R8: {=CHOOSE(G7,SCENARIOS!M5,SCENARIOS!M6,SCENARIOS!M7)} -> 0.18888349
D9: Costs of goods sold (% of revenue) | F9: % | H9: =-H26/H25 -> 0.52754384 | I9: =-I26/I25 -> 0.52454901 | J9: =-J26/J25 -> 0.53652795 | K9: =-K26/K25 -> 0.57380186 | L9: =-L26/L25 -> 0.5484111 | M9: =AVERAGE(H9:L9) -> 0.54216675 | N9: =M9 -> 0.54216675 | O9: =N9 -> 0.54216675 | P9: =O9 -> 0.54216675 | Q9: =P9 -> 0.54216675 | R9: =Q9 -> 0.54216675
D10: Salaries and Benefits (% of revenue) | F10: % | H10: =-H29/H25 -> 0.061676784 | I10: =-I29/I25 -> 0.079530122 | J10: =-J29/J25 -> 0.079184965 | K10: =-K29/K25 -> 0.087967447 | L10: =-L29/L25 -> 0.083084651 | M10: =AVERAGE(H10:L10) -> 0.078288794 | N10: =M10 -> 0.078288794 | O10: =N10 -> 0.078288794 | P10: =O10 -> 0.078288794 | Q10: =P10 -> 0.078288794 | R10: =Q10 -> 0.078288794
D11: Other SG&A expenses (% of revenue) | F11: % | H11: =-H30/H25 -> 0.175456 | I11: =-I30/I25 -> 0.19371259 | J11: =-J30/J25 -> 0.18548727 | K11: =-K30/K25 -> 0.15914447 | L11: =-L30/L25 -> 0.13801557 | M11: =AVERAGE(H11:L11) -> 0.17036318 | N11: =M11 -> 0.17036318 | O11: =N11 -> 0.17036318 | P11: =O11 -> 0.17036318 | Q11: =P11 -> 0.17036318 | R11: =Q11 -> 0.17036318
D12: Depreciation and amortization expense (% of PP&E) | F12: % | H12: - | I12: =-I32/I117 -> 0.062685706 | J12: =-J32/J117 -> 0.065338343 | K12: =-K32/K117 -> 0.059812455 | L12: =-L32/L117 -> 0.053695615 | M12: =AVERAGE(H12:L12) -> 0.06038303 | N12: =M12 -> 0.06038303 | O12: =N12 -> 0.06038303 | P12: =O12 -> 0.06038303 | Q12: =P12 -> 0.06038303 | R12: =Q12 -> 0.06038303
D13: Interest (% of debt) | F13: % | H13: - | I13: =-I34/I123 -> 0.046893308 | J13: =-J34/J123 -> 2.8578367 | K13: =-K34/K123 -> 1.6499458 | L13: =-L34/L123 -> 0.028702966 | M13: =8% -> 0.08 | N13: =M13 -> 0.08 | O13: =N13 -> 0.08 | P13: =O13 -> 0.08 | Q13: =P13 -> 0.08 | R13: =Q13 -> 0.08
D14: Other Income (Expenses) (% of revenue) | F14: % | H14: =H35/H25 -> 0.0040506988 | I14: =I35/I25 -> 0.0053107366 | J14: =J35/J25 -> 0.0070043106 | K14: =K35/K25 -> -0.034277176 | L14: =L35/L25 -> 0.016813797 | M14: =1% -> 0.01 | N14: =1% -> 0.01 | O14: =1% -> 0.01 | P14: =1% -> 0.01 | Q14: =1% -> 0.01 | R14: =1% -> 0.01
D15: Tax rate (% of earnings before tax) | F15: % | H15: =-H37/H36 -> 0.24715237 | I15: =-I37/I36 -> 0.21327736 | J15: =-J37/J36 -> 0.25748094 | K15: =-K37/K36 -> 0.40528417 | L15: =-L37/L36 -> 0.25788548 | M15: =AVERAGE(H15:L15) -> 0.27621606 | N15: =M15 -> 0.27621606 | O15: =N15 -> 0.27621606 | P15: =O15 -> 0.27621606 | Q15: =P15 -> 0.27621606 | R15: =Q15 -> 0.27621606
D16: Dividends payout | F16: % | H16: - | I16: - | J16: =-J99/J38 -> 0.13129715 | K16: =-K99/K38 -> 0.22442104 | L16: =-L99/L38 -> 0.076539559 | M16: =AVERAGE(H16:L16) -> 0.14408592 | N16: =M16 -> 0.14408592 | O16: =N16 -> 0.14408592 | P16: =O16 -> 0.14408592 | Q16: =P16 -> 0.14408592 | R16: =Q16 -> 0.14408592
D17: Accounts receivable | F17: Days | H17: =H47/H25*365 -> 129.33399 | I17: =I47/I25*365 -> 114.87653 | J17: =J47/J25*365 -> 136.27469 | K17: =K47/K25*365 -> 104.97727 | L17: =L47/L25*365 -> 105.30653 | M17: =AVERAGE(H17:L17) -> 118.1538 | N17: =M17 -> 118.1538 | O17: =N17 -> 118.1538 | P17: =O17 -> 118.1538 | Q17: =P17 -> 118.1538 | R17: =Q17 -> 118.1538
D18: Inventory | F18: Days | H18: =-H48/H26*365 -> 122.61712 | I18: =-I48/I26*365 -> 150.06206 | J18: =-J48/J26*365 -> 131.45592 | K18: =-K48/K26*365 -> 138.9594 | L18: =-L48/L26*365 -> 118.94305 | M18: =AVERAGE(H18:L18) -> 132.40751 | N18: =M18 -> 132.40751 | O18: =N18 -> 132.40751 | P18: =O18 -> 132.40751 | Q18: =P18 -> 132.40751 | R18: =Q18 -> 132.40751
D19: Accounts payable | F19: Days | H19: =-H61/H26*365 -> 172.20565 | I19: =-I61/I26*365 -> 158.41889 | J19: =-J61/J26*365 -> 156.68827 | K19: =-K61/K26*365 -> 119.34326 | L19: =-L61/L26*365 -> 103.14844 | M19: =AVERAGE(H19:L19) -> 141.9609 | N19: =M19 -> 141.9609 | O19: =N19 -> 141.9609 | P19: =O19 -> 141.9609 | Q19: =P19 -> 141.9609 | R19: =Q19 -> 141.9609
D20: Capital Asset Turnover Ratio | F20: Times | H20: =H25/H52 -> 2.1181372 | I20: =I25/I52 -> 2.7534968 | J20: =J25/J52 -> 2.2975986 | K20: =K25/K52 -> 1.4471528 | L20: =L25/L52 -> 1.5637816 | M20: =L20+0.3 -> 1.8637816 | N20: =M20+0.3 -> 2.1637816 | O20: =N20+0.3 -> 2.4637816 | P20: =O20+0.3 -> 2.7637816 | Q20: =P20+0.3 -> 3.0637816 | R20: =Q20+0.3 -> 3.3637816
A22: INCOME STATEMENT
B24: INCOME
D25: Revenue | F25: ₹ IN LAKHS | H25: ='HISTORICAL INFORMATION'!H6 -> 34060.79 | I25: ='HISTORICAL INFORMATION'!I6 -> 52013.5 | J25: ='HISTORICAL INFORMATION'!J6 -> 61673.45 | K25: ='HISTORICAL INFORMATION'!K6 -> 71747.45 | L25: ='HISTORICAL INFORMATION'!L6 -> 100687.55 | M25: =L25*(1+M8) -> 132895.07 | N25: =M25*(1+N8) -> 171154 | O25: =N25*(1+O8) -> 215499.9 | P25: =O25*(1+P8) -> 265752.22 | Q25: =P25*(1+Q8) -> 321525.78 | R25: =Q25*(1+R8) -> 382256.69
D26: Cost Of Goods Sold | F26: ₹ IN LAKHS | H26: =-SUM('HISTORICAL INFORMATION'!H10:H11) -> -17968.56 | I26: =-SUM('HISTORICAL INFORMATION'!I10:I11) -> -27283.63 | J26: =-SUM('HISTORICAL INFORMATION'!J10:J11) -> -33089.53 | K26: =-SUM('HISTORICAL INFORMATION'!K10:K11) -> -41168.82 | L26: =-SUM('HISTORICAL INFORMATION'!L10:L11) -> -55218.17 | M26: =-M25*M9 -> -72051.286 | N26: =-N25*N9 -> -92794.007 | O26: =-O25*O9 -> -116836.88 | P26: =-P25*P9 -> -144082.02 | Q26: =-Q25*Q9 -> -174320.59 | R26: =-R25*R9 -> -207246.87
D27: GROSS PROFIT | F27: ₹ IN LAKHS | H27: =SUM(H25:H26) -> 16092.23 | I27: =SUM(I25:I26) -> 24729.87 | J27: =SUM(J25:J26) -> 28583.92 | K27: =SUM(K25:K26) -> 30578.63 | L27: =SUM(L25:L26) -> 45469.38 | M27: =SUM(M25:M26) -> 60843.78 | N27: =SUM(N25:N26) -> 78359.99 | O27: =SUM(O25:O26) -> 98663.02 | ... R27: =SUM(R25:R26) -> 175009.82
B28: EXPENSES
D29: Salaries and Benefits | F29: ₹ IN LAKHS | H29: =-SUM('HISTORICAL INFORMATION'!H12) -> -2100.76 | I29: =-SUM('HISTORICAL INFORMATION'!I12) -> -4136.64 | J29: =-'HISTORICAL INFORMATION'!H12:L12 -> -4883.61 | K29: =-'HISTORICAL INFORMATION'!K12:M12 -> -6311.44 | L29: =-'HISTORICAL INFORMATION'!L12:N12 -> -8365.59 | M29: =-M25*M10 -> -10404.194 | N29: =-N25*N10 -> -13399.44 | O29: =-O25*O10 -> -16871.227 | P29: =-P25*P10 -> -20805.421 | Q29: =-Q25*Q10 -> -25171.866 | R29: =-R25*R10 -> -29926.415
D30: Other SG&A expenses | F30: ₹ IN LAKHS | H30: =-'HISTORICAL INFORMATION'!H15 -> -5976.17 | I30: =-'HISTORICAL INFORMATION'!I15 -> -10075.67 | J30: =-'HISTORICAL INFORMATION'!J15:L15 -> -11439.64 | K30: =-'HISTORICAL INFORMATION'!K15:M15 -> -11418.21 | L30: =-'HISTORICAL INFORMATION'!L15:N15 -> -13896.45 | M30: =-M25*M11 -> -22640.426 | N30: =-N25*N11 -> -29158.34 | O30: =-O25*O11 -> -36713.249 | P30: =-P25*P11 -> -45274.393 | Q30: =-Q25*Q11 -> -54776.155 | R30: =-R25*R11 -> -65122.467
D31: EBITDA | F31: ₹ IN LAKHS | H31: =SUM(H27:H30) -> 8015.3 | I31: =SUM(I27:I30) -> 10517.56 | J31: =SUM(J27:J30) -> 12260.67 | K31: =SUM(K27:K30) -> 12848.98 | L31: =SUM(L27:L30) -> 23207.34 | M31: =SUM(M27:M30) -> 27799.159 | N31: =SUM(N27:N30) -> 35802.211 | O31: =SUM(O27:O30) -> 45078.543 | ... R31: =SUM(R27:R30) -> 79960.941
D32: Depreciation and amortization expense | F32: ₹ IN LAKHS | H32: =-SUM('HISTORICAL INFORMATION'!H14) -> -418.81 | I32: =-SUM('HISTORICAL INFORMATION'!I14) -> -1008.02 | J32: =-'HISTORICAL INFORMATION'!J14:L14 -> -1234.24 | K32: =-'HISTORICAL INFORMATION'!K14:M14 -> -1605.52 | L32: =-'HISTORICAL INFORMATION'!L14:N14 -> -2662.14 | M32: =M119 -> -3887.8954 | N32: =N119 -> -4696.5957 | O32: =O119 -> -5480.6643 | P32: =P119 -> -6236.5667 | Q32: =Q119 -> -6957.8951 | R32: =R119 -> -7636.9785
D33: EBIT | F33: ₹ IN LAKHS | H33: =SUM(H31:H32) -> 7596.49 | I33: =SUM(I31:I32) -> 9509.54 | J33: =SUM(J31:J32) -> 11026.43 | K33: =SUM(K31:K32) -> 11243.46 | L33: =SUM(L31:L32) -> 20545.2 | M33: =SUM(M31:M32) -> 23911.263 | N33: =SUM(N31:N32) -> 31105.615 | O33: =SUM(O31:O32) -> 39597.879 | ... R33: =SUM(R31:R32) -> 72323.962
D34: Interest | F34: ₹ IN LAKHS | H34: =-SUM('HISTORICAL INFORMATION'!H13) -> -561.84 | I34: =-SUM('HISTORICAL INFORMATION'!I13) -> -640.73 | J34: =-'HISTORICAL INFORMATION'!J13:L13 -> -241.23 | K34: =-'HISTORICAL INFORMATION'!K13:M13 -> -594.03 | L34: =-'HISTORICAL INFORMATION'!L13:N13 -> -621.84 | M34: =M126 -> -103.5096 | N34: =N126 -> -103.5096 | O34: =O126 -> -103.5096 | P34: =P126 -> -103.5096 | Q34: =Q126 -> -103.5096 | R34: =R126 -> -103.5096
D35: Other Income (Expenses) | F35: ₹ IN LAKHS | H35: ='HISTORICAL INFORMATION'!H7+'HISTORICAL INFORMATION'!H18 -> 137.97 | I35: ='HISTORICAL INFORMATION'!I7+'HISTORICAL INFORMATION'!I18 -> 276.23 | J35: ='HISTORICAL INFORMATION'!J7+'HISTORICAL INFORMATION'!J18 -> 431.98 | K35: ='HISTORICAL INFORMATION'!K7+'HISTORICAL INFORMATION'!K18 -> -2459.3 | L35: ='HISTORICAL INFORMATION'!L7+'HISTORICAL INFORMATION'!L18 -> 1692.94 | M35: =M25*M14 -> 1328.9507 | N35: =N25*N14 -> 1711.54 | O35: =O25*O14 -> 2154.999 | P35: =P25*P14 -> 2657.5222 | Q35: =Q25*Q14 -> 3215.2578 | R35: =R25*R14 -> 3822.5669
D36: Earnings Before Tax | F36: ₹ IN LAKHS | H36: =SUM(H33:H35) -> 7172.62 | I36: =SUM(I33:I35) -> 9145.04 | J36: =SUM(J33:J35) -> 11217.18 | K36: =SUM(K33:K35) -> 8190.13 | L36: =SUM(L33:L35) -> 21616.3 | M36: =SUM(M33:M35) -> 25136.704 | N36: =SUM(N33:N35) -> 32713.645 | O36: =SUM(O33:O35) -> 41649.369 | ... R36: =SUM(R33:R35) -> 76043.019
D37: Taxes | F37: ₹ IN LAKHS | H37: =-'HISTORICAL INFORMATION'!H23 -> -1772.73 | I37: =-'HISTORICAL INFORMATION'!I23 -> -1950.43 | J37: =-'HISTORICAL INFORMATION'!J23:L23 -> -2888.21 | K37: =-'HISTORICAL INFORMATION'!K23:M23 -> -3319.33 | L37: =-'HISTORICAL INFORMATION'!L23:N23 -> -5574.53 | M37: =-M36*M15 -> -6943.1615 | N37: =-N36*N15 -> -9036.0343 | O37: =-O36*O15 -> -11504.225 | P37: =-P36*P15 -> -14337.777 | Q37: =-Q36*Q15 -> -17515.143 | R37: =-R36*R15 -> -21004.303
D38: Net earnings | F38: ₹ IN LAKHS | H38: =SUM(H36:H37) -> 5399.89 | I38: =SUM(I36:I37) -> 7194.61 | J38: =SUM(J36:J37) -> 8328.97 | K38: =SUM(K36:K37) -> 4870.8 | L38: =SUM(L36:L37) -> 16041.77 | M38: =SUM(M36:M37) -> 18193.543 | N38: =SUM(N36:N37) -> 23677.611 | O38: =SUM(O36:O37) -> 30145.144 | ... R38: =SUM(R36:R37) -> 55038.716
A41: BALANCE SHEET
B43: ASSESTS
C44: Current assests
D45: Cash | F45: ₹ IN LAKHS | H45: ='HISTORICAL INFORMATION'!H66 -> 268.46 | I45: ='HISTORICAL INFORMATION'!I66 -> 1029.66 | J45: ='HISTORICAL INFORMATION'!J66 -> 3053.26 | K45: ='HISTORICAL INFORMATION'!K66 -> 2970.44 | L45: ='HISTORICAL INFORMATION'!L66 -> 18522.43 | M45: =M105 -> 11007.131 | N45: =N105 -> 6446.3669 | O45: =O105 -> 6003.6823 | P45: =P105 -> 10660.517 | Q45: =Q105 -> 21434.233 | R45: =R105 -> 39327.923
D46: Bank deposits | F46: ₹ IN LAKHS | H46: ='HISTORICAL INFORMATION'!H67:L67 -> 0 | I46: ='HISTORICAL INFORMATION'!I67:M67 -> 8925.49 | J46: ='HISTORICAL INFORMATION'!J67:N67 -> 2813.76 | K46: ='HISTORICAL INFORMATION'!K67:O67 -> 2360.75 | L46: ='HISTORICAL INFORMATION'!L67:P67 -> 6370.4 | M46: =L46 -> 6370.4 | N46: =M46 -> 6370.4 | O46: =N46 -> 6370.4 | P46: =O46 -> 6370.4 | Q46: =P46 -> 6370.4 | R46: =Q46 -> 6370.4
D47: Accounts receivables | F47: ₹ IN LAKHS | H47: ='HISTORICAL INFORMATION'!H65 -> 12069.09 | I47: ='HISTORICAL INFORMATION'!I65 -> 16370.22 | J47: ='HISTORICAL INFORMATION'!J65 -> 23026.11 | K47: ='HISTORICAL INFORMATION'!K65 -> 20635.21 | L47: ='HISTORICAL INFORMATION'!L65 -> 29049.47 | M47: =M25*M17/365 -> 43019.335 | N47: =N25*N17/365 -> 55404.097 | O47: =O25*O17/365 -> 69759.268 | P47: =P25*P17/365 -> 86026.396 | Q47: =Q25*Q17/365 -> 104080.8 | R47: =R25*R17/365 -> 123739.95
D48: Inventory | F48: ₹ IN LAKHS | H48: ='HISTORICAL INFORMATION'!H63 -> 6036.31 | I48: ='HISTORICAL INFORMATION'!I63 -> 11217.09 | J48: ='HISTORICAL INFORMATION'!J63 -> 11917.3 | K48: ='HISTORICAL INFORMATION'!K63 -> 15673.41 | L48: ='HISTORICAL INFORMATION'!L63 -> 17994.02 | M48: =-M26*M18/365 -> 26137.347 | N48: =-N26*N18/365 -> 33661.982 | O48: =-O26*O18/365 -> 42383.783 | P48: =-P26*P18/365 -> 52267.236 | Q48: =-Q26*Q18/365 -> 63236.589 | R48: =-R26*R18/365 -> 75180.937
D49: Other current assests | F49: ₹ IN LAKHS | H49: ='HISTORICAL INFORMATION'!H70 -> 3215.83 | I49: ='HISTORICAL INFORMATION'!I70 -> 4855.23 | J49: ='HISTORICAL INFORMATION'!J70 -> 4446.79 | K49: ='HISTORICAL INFORMATION'!K70 -> 7535.49 | L49: ='HISTORICAL INFORMATION'!L70 -> 7011.3 | M49: =L49 -> 7011.3 | N49: =M49 -> 7011.3 | O49: =N49 -> 7011.3 | P49: =O49 -> 7011.3 | Q49: =P49 -> 7011.3 | R49: =Q49 -> 7011.3
C51: Non current assests
D52: Property and equipment | F52: ₹ IN LAKHS | H52: =SUM('HISTORICAL INFORMATION'!H49:H51,'HISTORICAL INFORMATION'!H53:H54) -> 16080.54 | I52: =SUM('HISTORICAL INFORMATION'!I49:I51,'HISTORICAL INFORMATION'!I53:I54) -> 18889.98 | J52: =SUM('HISTORICAL INFORMATION'!J49:J51,'HISTORICAL INFORMATION'!J53:J54) -> 26842.57 | K52: =SUM('HISTORICAL INFORMATION'!K49:K51,'HISTORICAL INFORMATION'!K53:K54) -> 49578.35 | L52: =SUM('HISTORICAL INFORMATION'!L49:L51,'HISTORICAL INFORMATION'!L53:L54) -> 64387.22 | M52: =M120 -> 77780.06 | N52: =N120 -> 90764.976 | O52: =O120 -> 103283.43 | P52: =P120 -> 115229.31 | Q52: =Q120 -> 126475.58 | R52: =R120 -> 136892.96
D53: Goodwill | F53: ₹ IN LAKHS | H53: ='HISTORICAL INFORMATION'!H52 -> 2570.11 | I53: ='HISTORICAL INFORMATION'!I52 -> 1859.56 | J53: ='HISTORICAL INFORMATION'!J52 -> 2032.29 | K53: ='HISTORICAL INFORMATION'!K52 -> 5680.09 | L53: ='HISTORICAL INFORMATION'!L52 -> 5680.09 | M53: =L53 -> 5680.09 | N53: =M53 -> 5680.09 | O53: =N53 -> 5680.09 | P53: =O53 -> 5680.09 | Q53: =P53 -> 5680.09 | R53: =Q53 -> 5680.09
D54: Financial assests | F54: ₹ IN LAKHS | H54: =SUM('HISTORICAL INFORMATION'!H56,'HISTORICAL INFORMATION'!H57,'HISTORICAL INFORMATION'!H58,'HISTORICAL INFORMATION'!H68) -> 446.89 | I54: =SUM('HISTORICAL INFORMATION'!I56,'HISTORICAL INFORMATION'!I57,'HISTORICAL INFORMATION'!I58,'HISTORICAL INFORMATION'!I68) -> 1322.43 | J54: =SUM('HISTORICAL INFORMATION'!J56,'HISTORICAL INFORMATION'!J57,'HISTORICAL INFORMATION'!J58,'HISTORICAL INFORMATION'!J68) -> 944.82 | K54: =SUM('HISTORICAL INFORMATION'!K56,'HISTORICAL INFORMATION'!K57,'HISTORICAL INFORMATION'!K58,'HISTORICAL INFORMATION'!K68) -> 432.31 | L54: =SUM('HISTORICAL INFORMATION'!L56,'HISTORICAL INFORMATION'!L57,'HISTORICAL INFORMATION'!L58,'HISTORICAL INFORMATION'!L68) -> 728.75 | M54: =L54 -> 728.75 | N54: =M54 -> 728.75 | O54: =N54 -> 728.75 | P54: =O54 -> 728.75 | Q54: =P54 -> 728.75 | R54: =Q54 -> 728.75
D55: Other non current assests | F55: ₹ IN LAKHS | H55: =SUM('HISTORICAL INFORMATION'!H59,'HISTORICAL INFORMATION'!H60,'HISTORICAL INFORMATION'!H69) -> 639.58 | I55: =SUM('HISTORICAL INFORMATION'!I59,'HISTORICAL INFORMATION'!I60,'HISTORICAL INFORMATION'!I69) -> 1418.63 | J55: =SUM('HISTORICAL INFORMATION'!J59,'HISTORICAL INFORMATION'!J60,'HISTORICAL INFORMATION'!J69) -> 1616.94 | K55: =SUM('HISTORICAL INFORMATION'!K59,'HISTORICAL INFORMATION'!K60,'HISTORICAL INFORMATION'!K69) -> 4724.28 | L55: =SUM('HISTORICAL INFORMATION'!L59,'HISTORICAL INFORMATION'!L60,'HISTORICAL INFORMATION'!L69) -> 5182.43 | M55: =L55 -> 5182.43 | N55: =M55 -> 5182.43 | O55: =N55 -> 5182.43 | P55: =O55 -> 5182.43 | Q55: =P55 -> 5182.43 | R55: =Q55 -> 5182.43
D56: Total Assets | F56: ₹ IN LAKHS | H56: =SUM(H45:H55) -> 41326.81 | I56: =SUM(I45:I55) -> 65888.29 | J56: =SUM(J45:J55) -> 76693.84 | K56: =SUM(K45:K55) -> 109590.33 | L56: =SUM(L45:L55) -> 154926.11 | M56: =SUM(M45:M55) -> 182916.84 | N56: =SUM(N45:N55) -> 211250.39 | O56: =SUM(O45:O55) -> 246403.14 | ... R56: =SUM(R45:R55) -> 400114.73
B59: LIABILITIES
C60: Current Liabilities
D61: Account Payables | F61: ₹ IN LAKHS | H61: =SUM('HISTORICAL INFORMATION'!H91:H92) -> 8477.5 | I61: =SUM('HISTORICAL INFORMATION'!I91:I92) -> 11841.76 | J61: =SUM('HISTORICAL INFORMATION'!J91:J92) -> 14204.77 | K61: =SUM('HISTORICAL INFORMATION'!K91:K92) -> 13460.88 | L61: =SUM('HISTORICAL INFORMATION'!L91:L92) -> 15604.57 | M61: =-M26*M19/365 -> 28023.193 | N61: =-N26*N19/365 -> 36090.742 | O61: =-O26*O19/365 -> 45441.833 | P61: =-P26*P19/365 -> 56038.391 | Q61: =-Q26*Q19/365 -> 67799.199 | R61: =-R26*R19/365 -> 80605.349
D62: Other current liabilities | F62: ₹ IN LAKHS | H62: =SUM('HISTORICAL INFORMATION'!H93:H94) -> 1612.59 | I62: =SUM('HISTORICAL INFORMATION'!I93:I94) -> 1064.69 | J62: =SUM('HISTORICAL INFORMATION'!J93:J94) -> 1782.4 | K62: =SUM('HISTORICAL INFORMATION'!K93:K94) -> 4755.59 | L62: =SUM('HISTORICAL INFORMATION'!L93:L94) -> 3801.74 | M62: =L62 -> 3801.74 | N62: =M62 -> 3801.74 | O62: =N62 -> 3801.74 | P62: =O62 -> 3801.74 | Q62: =P62 -> 3801.74 | R62: =Q62 -> 3801.74
C63: Non Current Liabilities
D64: Debt | F64: ₹ IN LAKHS | H64: =SUM('HISTORICAL INFORMATION'!H82,'HISTORICAL INFORMATION'!H83,'HISTORICAL INFORMATION'!H89) -> 13663.57 | I64: =SUM('HISTORICAL INFORMATION'!I82,'HISTORICAL INFORMATION'!I83,'HISTORICAL INFORMATION'!I89) -> 84.41 | J64: =SUM('HISTORICAL INFORMATION'!J82,'HISTORICAL INFORMATION'!J83,'HISTORICAL INFORMATION'!J89) -> 360.03 | K64: =SUM('HISTORICAL INFORMATION'!K82,'HISTORICAL INFORMATION'!K83,'HISTORICAL INFORMATION'!K89) -> 21664.66 | L64: =SUM('HISTORICAL INFORMATION'!L82,'HISTORICAL INFORMATION'!L83,'HISTORICAL INFORMATION'!L89) -> 1293.87 | M64: =M125 -> 1293.87 | N64: =N125 -> 1293.87 | O64: =O125 -> 1293.87 | P64: =P125 -> 1293.87 | Q64: =Q125 -> 1293.87 | R64: =R125 -> 1293.87
D65: Other non current liabilities | F65: ₹ IN LAKHS | H65: =SUM('HISTORICAL INFORMATION'!H84,'HISTORICAL INFORMATION'!H85,'HISTORICAL INFORMATION'!H95) -> 879.85 | I65: =SUM('HISTORICAL INFORMATION'!I84,'HISTORICAL INFORMATION'!I85,'HISTORICAL INFORMATION'!I95) -> 670.03 | J65: =SUM('HISTORICAL INFORMATION'!J84,'HISTORICAL INFORMATION'!J85,'HISTORICAL INFORMATION'!J95) -> 950.72 | K65: =SUM('HISTORICAL INFORMATION'!K84,'HISTORICAL INFORMATION'!K85,'HISTORICAL INFORMATION'!K95) -> 1433.4 | L65: =SUM('HISTORICAL INFORMATION'!L84,'HISTORICAL INFORMATION'!L85,'HISTORICAL INFORMATION'!L95) -> 2217.89 | M65: =L65 -> 2217.89 | N65: =M65 -> 2217.89 | O65: =N65 -> 2217.89 | P65: =O65 -> 2217.89 | Q65: =P65 -> 2217.89 | R65: =Q65 -> 2217.89
D66: Total Liabilities | F66: ₹ IN LAKHS | H66: =SUM(H61:H65) -> 24633.51 | I66: =SUM(I61:I65) -> 13660.89 | J66: =SUM(J61:J65) -> 17297.92 | K66: =SUM(K61:K65) -> 41314.53 | L66: =SUM(L61:L65) -> 22918.07 | M66: =SUM(M61:M65) -> 35336.693 | N66: =SUM(N61:N65) -> 43404.242 | O66: =SUM(O61:O65) -> 52755.333 | ... R66: =SUM(R61:R65) -> 87918.849
C67: Shareholder's Equity
D68: Equity Capital | F68: ₹ IN LAKHS | H68: ='HISTORICAL INFORMATION'!H75 -> 3150 | I68: ='HISTORICAL INFORMATION'!I75 -> 3643.71 | J68: ='HISTORICAL INFORMATION'!J75 -> 3643.71 | K68: ='HISTORICAL INFORMATION'!K75 -> 3688.06 | L68: ='HISTORICAL INFORMATION'!L75 -> 4093.45 | M68: =L68 -> 4093.45 | N68: =M68 -> 4093.45 | O68: =N68 -> 4093.45 | P68: =O68 -> 4093.45 | Q68: =P68 -> 4093.45 | R68: =Q68 -> 4093.45
D69: Retained earnings | F69: ₹ IN LAKHS | H69: ='HISTORICAL INFORMATION'!H76 -> 13543.32 | I69: ='HISTORICAL INFORMATION'!I76 -> 48583.69 | J69: ='HISTORICAL INFORMATION'!J76 -> 55752.21 | K69: ='HISTORICAL INFORMATION'!K76 -> 63711.68 | L69: ='HISTORICAL INFORMATION'!L76 -> 126869.42 | M69: =L69+M38+M99 -> 142441.53 | N69: =M69+N38+N99 -> 162707.53 | O69: =N69+O38+O99 -> 188509.18 | P69: =O69+P38+P99 -> 220665.92 | Q69: =P69+Q38+Q99 -> 259948.85 | R69: =Q69+R38+R99 -> 307057.27
D70: Total Shareholder's Equity | F70: ₹ IN LAKHS | H70: =SUM(H68:H69) -> 16693.32 | I70: =SUM(I68:I69) -> 52227.4 | J70: =SUM(J68:J69) -> 59395.92 | K70: =SUM(K68:K69) -> 67399.74 | L70: =SUM(L68:L69) -> 130962.87 | M70: =SUM(M68:M69) -> 146534.98 | N70: =SUM(N68:N69) -> 166800.98 | O70: =SUM(O68:O69) -> 192602.63 | ... R70: =SUM(R68:R69) -> 311150.72
D71: Non controlling interests | F71: ₹ IN LAKHS | H71: ='HISTORICAL INFORMATION'!H78 -> 0 | I71: ='HISTORICAL INFORMATION'!I78 -> 0 | J71: ='HISTORICAL INFORMATION'!J78 -> 0 | K71: ='HISTORICAL INFORMATION'!K78 -> 876.06 | L71: ='HISTORICAL INFORMATION'!L78 -> 1045.17 | M71: =L71 -> 1045.17 | N71: =M71 -> 1045.17 | O71: =N71 -> 1045.17 | P71: =O71 -> 1045.17 | Q71: =P71 -> 1045.17 | R71: =Q71 -> 1045.17
D72: Total Liabilities & Shareholder's Equity | F72: ₹ IN LAKHS | H72: =SUM(H66,H70,H71) -> 41326.83 | I72: =SUM(I66,I70,I71) -> 65888.29 | J72: =SUM(J66,J70,J71) -> 76693.84 | K72: =SUM(K66,K70,K71) -> 109590.33 | L72: =SUM(L66,L70,L71) -> 154926.11 | M72: =SUM(M66,M70,M71) -> 182916.84 | N72: =SUM(N66,N70,N71) -> 211250.39 | O72: =SUM(O66,O70,O71) -> 246403.14 | ... R72: =SUM(R66,R70,R71) -> 400114.73
D74: Check | H74: =H72-H56 -> 0.02 | I74: =I72-I56 -> 0 | J74: =J72-J56 -> 0 | K74: =K72-K56 -> 0 | L74: =L72-L56 -> 0 | M74: =M72-M56 -> 0 | N74: =N72-N56 -> 0 | O74: =O72-O56 -> 0 | ... R74: =R72-R56 -> 0
A76: CASHFLOW STATEMENT
C78: Operating Cashflow
D79: Net earnings | F79: ₹ IN LAKHS | H79: =SUM('HISTORICAL INFORMATION'!H106,'HISTORICAL INFORMATION'!H132) -> 5755.1 | I79: =SUM('HISTORICAL INFORMATION'!I106,'HISTORICAL INFORMATION'!I132) -> 6863.66 | J79: =SUM('HISTORICAL INFORMATION'!J106,'HISTORICAL INFORMATION'!J132) -> 8771.74 | K79: =SUM('HISTORICAL INFORMATION'!K106,'HISTORICAL INFORMATION'!K132) -> 5755.51 | L79: =SUM('HISTORICAL INFORMATION'!L106,'HISTORICAL INFORMATION'!L132) -> 16942.53 | M79: =M38 -> 18193.543 | N79: =N38 -> 23677.611 | O79: =O38 -> 30145.144 | P79: =P38 -> 37570.055 | Q79: =Q38 -> 45895.881 | R79: =R38 -> 55038.716
D80: Plus: Depreciation and amortisation | F80: ₹ IN LAKHS | H80: ='HISTORICAL INFORMATION'!H108 -> 418.8 | I80: ='HISTORICAL INFORMATION'!I108 -> 1008.02 | J80: ='HISTORICAL INFORMATION'!J108 -> 1234.24 | K80: ='HISTORICAL INFORMATION'!K108 -> 1605.52 | L80: ='HISTORICAL INFORMATION'!L108 -> 2662.14 | M80: =-M119 -> 3887.8954 | N80: =-N119 -> 4696.5957 | O80: =-O119 -> 5480.6643 | P80: =-P119 -> 6236.5667 | Q80: =-Q119 -> 6957.8951 | R80: =-R119 -> 7636.9785
D81: Plus/less: Adjustments for non operating items | F81: ₹ IN LAKHS | H81: ='HISTORICAL INFORMATION'!H119-'HISTORICAL INFORMATION'!H108 -> 382.81 | I81: ='HISTORICAL INFORMATION'!I119-'HISTORICAL INFORMATION'!I108 -> 356.29 | J81: ='HISTORICAL INFORMATION'!J119-'HISTORICAL INFORMATION'!J108 -> 175.1 | K81: ='HISTORICAL INFORMATION'!K119-'HISTORICAL INFORMATION'!K108 -> 3373.7 | L81: ='HISTORICAL INFORMATION'!L119-'HISTORICAL INFORMATION'!L108 -> -769.8 | M81: =-M34-M35 -> -1225.4411 | N81: =-N34-N35 -> -1608.0304 | O81: =-O34-O35 -> -2051.4894 | P81: =-P34-P35 -> -2554.0126 | Q81: =-Q34-Q35 -> -3111.7482 | R81: =-R34-R35 -> -3719.0573
D82: Plus/less: Adjustments for Operating assets& liabilities (WC) | F82: ₹ IN LAKHS | H82: ='HISTORICAL INFORMATION'!H130 -> -3760.66 | I82: ='HISTORICAL INFORMATION'!I130 -> -9421.45 | J82: ='HISTORICAL INFORMATION'!J130 -> -3628.08 | K82: ='HISTORICAL INFORMATION'!K130 -> 1782.24 | L82: ='HISTORICAL INFORMATION'!L130 -> -7000.6 | M82: =M114 -> -9694.5685 | N82: =N114 -> -11841.849 | O82: =O114 -> -13725.88 | P82: =P114 -> -15554.024 | Q82: =Q114 -> -17262.953 | R82: =R114 -> -18797.344
D83: Cash from operations | F83: ₹ IN LAKHS | H83: =SUM(H79:H82) -> 2796.05 | I83: =SUM(I79:I82) -> -1193.48 | J83: =SUM(J79:J82) -> 6553 | K83: =SUM(K79:K82) -> 12516.97 | L83: =SUM(L79:L82) -> 11834.27 | M83: =SUM(M79:M82) -> 11161.429 | N83: =SUM(N79:N82) -> 14924.327 | O83: =SUM(O79:O82) -> 19848.438 | ... R83: =SUM(R79:R82) -> 40159.293
C85: Investing Cashflow
D86: Investments in Property & Equipment | F86: ₹ IN LAKHS | H86: ='HISTORICAL INFORMATION'!H136 -> -10711.48 | I86: ='HISTORICAL INFORMATION'!I136 -> -3375.81 | J86: ='HISTORICAL INFORMATION'!J136 -> -7834.94 | K86: ='HISTORICAL INFORMATION'!K136 -> -31467.75 | L86: ='HISTORICAL INFORMATION'!L136 -> -19464.29 | M86: =-M118 -> -17280.735 | N86: =-N118 -> -17681.512 | O86: =-O118 -> -17999.122 | P86: =-P118 -> -18182.448 | Q86: =-Q118 -> -18204.158 | R86: =-R118 -> -18054.357
D87: Sale of property, plant and equipment | F87: ₹ IN LAKHS | H87: ='HISTORICAL INFORMATION'!H138 -> 253.75 | I87: ='HISTORICAL INFORMATION'!I138 -> 0 | J87: ='HISTORICAL INFORMATION'!J138 -> 0 | K87: ='HISTORICAL INFORMATION'!K138 -> 0 | L87: ='HISTORICAL INFORMATION'!L138 -> 0 | M87: ='HISTORICAL INFORMATION'!M138 -> 0 | N87: ='HISTORICAL INFORMATION'!N138 -> 0 | O87: ='HISTORICAL INFORMATION'!O138 -> 0 | ... R87: ='HISTORICAL INFORMATION'!R138 -> 0
D88: Purchase/ investments in FD | F88: ₹ IN LAKHS | H88: =SUM('HISTORICAL INFORMATION'!H135,'HISTORICAL INFORMATION'!H141) -> 317.69 | I88: =SUM('HISTORICAL INFORMATION'!I135,'HISTORICAL INFORMATION'!I141) -> -8953.94 | J88: =SUM('HISTORICAL INFORMATION'!J135,'HISTORICAL INFORMATION'!J141) -> 6117.97 | K88: =SUM('HISTORICAL INFORMATION'!K135,'HISTORICAL INFORMATION'!K141) -> -5300.68 | L88: =SUM('HISTORICAL INFORMATION'!L135,'HISTORICAL INFORMATION'!L141) -> -4009.65 | M88: =L54-M54 -> 0 | N88: =M54-N54 -> 0 | O88: =N54-O54 -> 0 | P88: =O54-P54 -> 0 | Q88: =P54-Q54 -> 0 | R88: =Q54-R54 -> 0
D89: Right of Use Asset | F89: ₹ IN LAKHS | H89: ='HISTORICAL INFORMATION'!H140 -> 0 | I89: ='HISTORICAL INFORMATION'!I140 -> - | J89: ='HISTORICAL INFORMATION'!J140 -> -1805.35 | K89: ='HISTORICAL INFORMATION'!K140 -> 0 | L89: ='HISTORICAL INFORMATION'!L140 -> 0
D90: Change in other non current assets | F90: ₹ IN LAKHS | H90: ='HISTORICAL INFORMATION'!H142 -> 0 | I90: ='HISTORICAL INFORMATION'!I142 -> 0 | J90: ='HISTORICAL INFORMATION'!J142 -> 0 | K90: ='HISTORICAL INFORMATION'!K142 -> 0 | L90: ='HISTORICAL INFORMATION'!L142 -> 0
D91: Dividend received | F91: ₹ IN LAKHS | H91: ='HISTORICAL INFORMATION'!H143 -> 0 | I91: ='HISTORICAL INFORMATION'!I143 -> 0 | J91: ='HISTORICAL INFORMATION'!J143 -> 0.03 | K91: ='HISTORICAL INFORMATION'!K143 -> 0 | L91: ='HISTORICAL INFORMATION'!L143 -> 0.04
D92: Interest received | F92: ₹ IN LAKHS | H92: ='HISTORICAL INFORMATION'!H144 -> 19.53 | I92: ='HISTORICAL INFORMATION'!I144 -> 258.18 | J92: ='HISTORICAL INFORMATION'!J144 -> 217.89 | K92: ='HISTORICAL INFORMATION'!K144 -> 229.08 | L92: ='HISTORICAL INFORMATION'!L144 -> 1079.58 | M92: =M35 -> 1328.9507 | N92: =N35 -> 1711.54 | O92: =O35 -> 2154.999 | P92: =P35 -> 2657.5222 | Q92: =Q35 -> 3215.2578 | R92: =R35 -> 3822.5669
D93: Cash from investing | F93: ₹ IN LAKHS | H93: =SUM(H86:H92) -> -10120.51 | I93: =SUM(I86:I92) -> -12071.57 | J93: =SUM(J86:J92) -> -3304.4 | K93: =SUM(K86:K92) -> -36539.35 | L93: =SUM(L86:L92) -> -22394.32 | M93: =SUM(M86:M92) -> -15951.784 | N93: =SUM(N86:N92) -> -15969.972 | O93: =SUM(O86:O92) -> -15844.123 | ... R93: =SUM(R86:R92) -> -14231.79
C95: Financing Cashflow
D96: Issuance(Repayment) of debt | F96: ₹ IN LAKHS | H96: =SUM('HISTORICAL INFORMATION'!H147,'HISTORICAL INFORMATION'!H148,'HISTORICAL INFORMATION'!H150) -> 7721.63 | I96: =SUM('HISTORICAL INFORMATION'!I147,'HISTORICAL INFORMATION'!I148,'HISTORICAL INFORMATION'!I150) -> -13579.16 | J96: =SUM('HISTORICAL INFORMATION'!J147,'HISTORICAL INFORMATION'!J148,'HISTORICAL INFORMATION'!J150) -> 275.64 | K96: =SUM('HISTORICAL INFORMATION'!K147,'HISTORICAL INFORMATION'!K148,'HISTORICAL INFORMATION'!K150) -> 21807.75 | L96: =SUM('HISTORICAL INFORMATION'!L147,'HISTORICAL INFORMATION'!L148,'HISTORICAL INFORMATION'!L150) -> -20879.87 | M96: =M124 -> 0 | N96: =N124 -> 0 | O96: =O124 -> 0 | P96: =P124 -> 0 | Q96: =Q124 -> 0 | R96: =R124 -> 0
D97: Issue of equity shares/ expenses | F97: ₹ IN LAKHS | H97: =SUM('HISTORICAL INFORMATION'!H153,'HISTORICAL INFORMATION'!H154,'HISTORICAL INFORMATION'!H155) -> 0 | I97: =SUM('HISTORICAL INFORMATION'!I153,'HISTORICAL INFORMATION'!I154,'HISTORICAL INFORMATION'!I155) -> 28150.32 | J97: =SUM('HISTORICAL INFORMATION'!J153,'HISTORICAL INFORMATION'!J154,'HISTORICAL INFORMATION'!J155) -> -165.84 | K97: =SUM('HISTORICAL INFORMATION'!K153,'HISTORICAL INFORMATION'!K154,'HISTORICAL INFORMATION'!K155) -> 5294.63 | L97: =SUM('HISTORICAL INFORMATION'!L153,'HISTORICAL INFORMATION'!L154,'HISTORICAL INFORMATION'!L155) -> 48839.53
D98: Interest paid | F98: ₹ IN LAKHS | H98: =SUM('HISTORICAL INFORMATION'!H149) -> -510.8 | I98: =SUM('HISTORICAL INFORMATION'!I149) -> -544.91 | J98: =SUM('HISTORICAL INFORMATION'!J149) -> -241.23 | K98: =SUM('HISTORICAL INFORMATION'!K149) -> -594.03 | L98: =SUM('HISTORICAL INFORMATION'!L149) -> -619.79 | M98: =M126 -> -103.5096 | N98: =N126 -> -103.5096 | O98: =O126 -> -103.5096 | P98: =P126 -> -103.5096 | Q98: =Q126 -> -103.5096 | R98: =R126 -> -103.5096
D99: Dividend paid | F99: ₹ IN LAKHS | H99: =SUM('HISTORICAL INFORMATION'!H152) -> 0 | I99: =SUM('HISTORICAL INFORMATION'!I152) -> 0 | J99: =SUM('HISTORICAL INFORMATION'!J152) -> -1093.57 | K99: =SUM('HISTORICAL INFORMATION'!K152) -> -1093.11 | L99: =SUM('HISTORICAL INFORMATION'!L152) -> -1227.83 | M99: =-M38*M16 -> -2621.4333 | N99: =-N38*N16 -> -3411.6103 | O99: =-O38*O16 -> -4343.4907 | P99: =-P38*P16 -> -5413.3158 | Q99: =-Q38*Q16 -> -6612.95 | R99: =-R38*R16 -> -7930.3038
D100: Withdrawal of partners capital | F100: ₹ IN LAKHS | H100: =SUM('HISTORICAL INFORMATION'!H151) -> 0 | I100: =SUM('HISTORICAL INFORMATION'!I151) -> 0 | J100: =SUM('HISTORICAL INFORMATION'!J151) -> 0 | K100: =SUM('HISTORICAL INFORMATION'!K151) -> -1478.88 | L100: =SUM('HISTORICAL INFORMATION'!L151) -> 0 | M100: =SUM('HISTORICAL INFORMATION'!M151) -> 0 | N100: =SUM('HISTORICAL INFORMATION'!N151) -> 0 | O100: =SUM('HISTORICAL INFORMATION'!O151) -> 0 | ... R100: =SUM('HISTORICAL INFORMATION'!R151) -> 0
D101: Cash from financing | F101: ₹ IN LAKHS | H101: =SUM(H96:H100) -> 7210.83 | I101: =SUM(I96:I100) -> 14026.25 | J101: =SUM(J96:J100) -> -1225 | K101: =SUM(K96:K100) -> 23936.36 | L101: =SUM(L96:L100) -> 26112.04 | M101: =SUM(M96:M100) -> -2724.9429 | N101: =SUM(N96:N100) -> -3515.1199 | O101: =SUM(O96:O100) -> -4447.0003 | ... R101: =SUM(R96:R100) -> -8033.8134
D103: Net increase / (decrease) in cash and cash equivalents (A+B+C) | F103: ₹ IN LAKHS | H103: =SUM(H83,H93,H101) -> -113.63 | I103: =SUM(I83,I93,I101) -> 761.2 | J103: =SUM(J83,J93,J101) -> 2023.6 | K103: =SUM(K83,K93,K101) -> -86.02 | L103: =SUM(L83,L93,L101) -> 15551.99 | M103: =SUM(M83,M93,M101) -> -7515.2985 | N103: =SUM(N83,N93,N101) -> -4560.7646 | O103: =SUM(O83,O93,O101) -> -442.68465 | ... R103: =SUM(R83,R93,R101) -> 17893.69
D104: Operating Cash Balance | F104: ₹ IN LAKHS | H104: =SUM('HISTORICAL INFORMATION'!H158:H159) -> 382.22 | I104: =SUM('HISTORICAL INFORMATION'!I158:I159) -> 268.46 | J104: =SUM('HISTORICAL INFORMATION'!J158:J159) -> 1029.66 | K104: =SUM('HISTORICAL INFORMATION'!K158:K159) -> 3056.46 | L104: =SUM('HISTORICAL INFORMATION'!L158:L159) -> 2970.44 | M104: =L105 -> 18522.43 | N104: =M105 -> 11007.131 | O104: =N105 -> 6446.3669 | P104: =O105 -> 6003.6823 | Q104: =P105 -> 10660.517 | R104: =Q105 -> 21434.233
D105: Closing Cash Balance | F105: ₹ IN LAKHS | H105: =SUM(H103:H104) -> 268.59 | I105: =SUM(I103:I104) -> 1029.66 | J105: =SUM(J103:J104) -> 3053.26 | K105: =SUM(K103:K104) -> 2970.44 | L105: =SUM(L103:L104) -> 18522.43 | M105: =SUM(M103:M104) -> 11007.131 | N105: =SUM(N103:N104) -> 6446.3669 | O105: =SUM(O103:O104) -> 6003.6823 | ... R105: =SUM(R103:R104) -> 39327.923
A108: SUPPORTING SCHEDULES
C109: Working Capital
D110: Account receivables | F110: ₹ IN LAKHS | H110: ='HISTORICAL INFORMATION'!H122 -> -6416.98 | I110: ='HISTORICAL INFORMATION'!I122 -> -4145.5 | J110: ='HISTORICAL INFORMATION'!J122 -> -6442.66 | K110: ='HISTORICAL INFORMATION'!K122 -> 3000.27 | L110: ='HISTORICAL INFORMATION'!L122 -> -8011.08 | M110: =L47-M47 -> -13969.865 | N110: =M47-N47 -> -12384.762 | O110: =N47-O47 -> -14355.171 | P110: =O47-P47 -> -16267.129 | Q110: =P47-Q47 -> -18054.407 | R110: =Q47-R47 -> -19659.146
D111: Inventory | F111: ₹ IN LAKHS | H111: ='HISTORICAL INFORMATION'!H125 -> -802.14 | I111: ='HISTORICAL INFORMATION'!I125 -> -5180.78 | J111: ='HISTORICAL INFORMATION'!J125 -> -700.21 | K111: ='HISTORICAL INFORMATION'!K125 -> -3508.19 | L111: ='HISTORICAL INFORMATION'!L125 -> -2320.61 | M111: =L48-M48 -> -8143.3266 | N111: =M48-N48 -> -7524.6355 | O111: =N48-O48 -> -8721.8008 | P111: =O48-P48 -> -9883.4531 | Q111: =P48-Q48 -> -10969.353 | R111: =Q48-R48 -> -11944.348
D112: Account Payable | F112: ₹ IN LAKHS | H112: ='HISTORICAL INFORMATION'!H127 -> 3342.37 | I112: ='HISTORICAL INFORMATION'!I127 -> 3267.88 | J112: ='HISTORICAL INFORMATION'!J127 -> 2363.01 | K112: ='HISTORICAL INFORMATION'!K127 -> 2359.61 | L112: ='HISTORICAL INFORMATION'!L127 -> 2143.69 | M112: =M61-L61 -> 12418.623 | N112: =N61-M61 -> 8067.5486 | O112: =O61-N61 -> 9351.0911 | P112: =P61-O61 -> 10596.558 | Q112: =Q61-P61 -> 11760.808 | R112: =R61-Q61 -> 12806.15
D113: Others | F113: ₹ IN LAKHS | H113: =SUM('HISTORICAL INFORMATION'!H123,'HISTORICAL INFORMATION'!H124,'HISTORICAL INFORMATION'!H126,'HISTORICAL INFORMATION'!H128,'HISTORICAL INFORMATION'!H129) -> 116.09 | I113: =SUM('HISTORICAL INFORMATION'!I123,'HISTORICAL INFORMATION'!I124,'HISTORICAL INFORMATION'!I126,'HISTORICAL INFORMATION'!I128,'HISTORICAL INFORMATION'!I129) -> -3363.05 | J113: =SUM('HISTORICAL INFORMATION'!J123,'HISTORICAL INFORMATION'!J124,'HISTORICAL INFORMATION'!J126,'HISTORICAL INFORMATION'!J128,'HISTORICAL INFORMATION'!J129) -> 1151.78 | K113: =SUM('HISTORICAL INFORMATION'!K123,'HISTORICAL INFORMATION'!K124,'HISTORICAL INFORMATION'!K126,'HISTORICAL INFORMATION'!K128,'HISTORICAL INFORMATION'!K129) -> -69.45 | L113: =SUM('HISTORICAL INFORMATION'!L123,'HISTORICAL INFORMATION'!L124,'HISTORICAL INFORMATION'!L126,'HISTORICAL INFORMATION'!L128,'HISTORICAL INFORMATION'!L129) -> 1187.4 | M113: =(L49-M49)+(M62-L62) -> 0 | N113: =(M49-N49)+(N62-M62) -> 0 | O113: =(N49-O49)+(O62-N62) -> 0 | P113: =(O49-P49)+(P62-O62) -> 0 | Q113: =(P49-Q49)+(Q62-P62) -> 0 | R113: =(Q49-R49)+(R62-Q62) -> 0
D114: Total | F114: ₹ IN LAKHS | H114: =SUM(H110:H113) -> -3760.66 | I114: =SUM(I110:I113) -> -9421.45 | J114: =SUM(J110:J113) -> -3628.08 | K114: =SUM(K110:K113) -> 1782.24 | L114: =SUM(L110:L113) -> -7000.6 | M114: =SUM(M110:M113) -> -9694.5685 | N114: =SUM(N110:N113) -> -11841.849 | O114: =SUM(O110:O113) -> -13725.88 | ... R114: =SUM(R110:R113) -> -18797.344
C116: Depreciation Schedule
D117: PPE opening | F117: ₹ IN LAKHS | I117: =H120 -> 16080.54 | J117: =I120 -> 18889.98 | K117: =J120 -> 26842.57 | L117: =K120 -> 49578.35 | M117: =L120 -> 64387.22 | N117: =M120 -> 77780.06 | O117: =N120 -> 90764.976 | P117: =O120 -> 103283.43 | ... R117: =Q120 -> 126475.58
D118: Plus Capex | F118: ₹ IN LAKHS | I118: =I120-I117-I119 -> 3817.46 | J118: =J120-J117-J119 -> 9186.83 | K118: =K120-K117-K119 -> 24341.3 | L118: =L120-L117-L119 -> 17471.01 | M118: =(M25-L25)/M20 -> 17280.735 | N118: =(N25-M25)/N20 -> 17681.512 | O118: =(O25-N25)/O20 -> 17999.122 | P118: =(P25-O25)/P20 -> 18182.448 | Q118: =(Q25-P25)/Q20 -> 18204.158 | R118: =(R25-Q25)/R20 -> 18054.357
D119: Less Depreciation | F119: ₹ IN LAKHS | H119: =-H80 -> -418.8 | I119: =-I80 -> -1008.02 | J119: =-J80 -> -1234.24 | K119: =-K80 -> -1605.52 | L119: =-L80 -> -2662.14 | M119: =-M117*M12 -> -3887.8954 | N119: =-N117*N12 -> -4696.5957 | O119: =-O117*O12 -> -5480.6643 | P119: =-P117*P12 -> -6236.5667 | Q119: =-Q117*Q12 -> -6957.8951 | R119: =-R117*R12 -> -7636.9785
...

Sheet SCENARIOS
A1: ACUTAAS CHEMICALS LIMITED
A2: SCENARIOS
C4: Scenarios | E4: Growth % | H4: 2026 | I4: 2027 | J4: 2028 | K4: 2029 | L4: 2030 | M4: 2031
D5: Base Case | E5: =AVERAGE(MODEL!H8:L8) -> 0.31987586 | H5: =E5 -> 0.31987586 | I5: =H5*(1-$E$8) -> 0.28788827 | J5: =I5*(1-$E$8) -> 0.25909944 | K5: =J5*(1-$E$8) -> 0.2331895 | L5: =K5*(1-$E$8) -> 0.20987055 | M5: =L5*(1-$E$8) -> 0.18888349
D6: Bull Case | E6: 0.35 | H6: =E6 -> 0.35 | I6: =H6*(1-$E$8) -> 0.315 | J6: =I6*(1-$E$8) -> 0.2835 | K6: =J6*(1-$E$8) -> 0.25515 | L6: =K6*(1-$E$8) -> 0.229635 | M6: =L6*(1-$E$8) -> 0.2066715
D7: Bear Case | E7: =MIN(MODEL!I8:L8) -> 0.16334419 | H7: =E7 -> 0.16334419 | I7: =H7*(1-$E$8) -> 0.14700977 | J7: =I7*(1-$E$8) -> 0.1323088 | K7: =J7*(1-$E$8) -> 0.11907792 | L7: =K7*(1-$E$8) -> 0.10717013 | M7: =L7*(1-$E$8) -> 0.096453113
D8: Annual Growth Tapering | E8: 0.1

Sheet COMP
A1: ACUTAAS CHEMICALS LIMITED
A2: COMPS VALUATION
J5: MARKET DATA | P5: FINANCIAL DATA | T5: VALUATION
H6: Price | I6: Shares | J6: Market Cap | K6: Debt | L6: Cash & | M6: EV | O6: Sales | P6: EBITDA | Q6: Earnings | S6: EV/Sales | T6: EV/EBITDA | U6: P/E
D7: Company Name | F7: Ticker | H7: (₹/Share) | I7: Lakhs | J7: ₹ Lakhs | K7: ₹ Lakhs | L7: Equivalents | M7: ₹ Lakhs | O7: ₹ Lakhs | P7: ₹ Lakhs | Q7: ₹ Lakhs | S7: x | T7: x | U7: x
D8: Neuland Laboratories Limited | F8: ='COMP DATA'!H8 -> 524558 | H8: ='COMP DATA'!I8 -> 18781.85 | I8: ='COMP DATA'!J8*10 -> 128.29946 | J8: =H8*I8 -> 2409701.2 | K8: ='COMP DATA'!K8*10 -> 30711.862 | L8: ='COMP DATA'!L8*10 -> 36185.327 | M8: =J8+K8-L8 -> 2404227.7 | O8: ='COMP DATA'!M8*10 -> 206224.3 | P8: ='COMP DATA'!N8*10 -> 58564.638 | Q8: ='COMP DATA'!O8*10 -> 37106.208 | S8: =M8/O8 -> 11.658314 | T8: =M8/P8 -> 41.05255 | U8: =J8/Q8 -> 64.940649
D9: Ipca Laboratories Limited | F9: ='COMP DATA'!H9 -> IPCALAB | H9: ='COMP DATA'!I9 -> 1696.4 | I9: ='COMP DATA'!J9*10 -> 2536.9497 | J9: =H9*I9 -> 4303681.6 | K9: ='COMP DATA'!K9*10 -> 82445.462 | L9: ='COMP DATA'!L9*10 -> 121746.6 | M9: =J9+K9-L9 -> 4264380.4 | O9: ='COMP DATA'!M9*10 -> 983352.46 | P9: ='COMP DATA'!N9*10 -> 201695.55 | Q9: ='COMP DATA'!O9*10 -> 116326.43 | S9: =M9/O9 -> 4.3365737 | T9: =M9/P9 -> 21.14266 | U9: =J9/Q9 -> 36.996592
D10: Granules India Limited | F10: ='COMP DATA'!H10 -> 532482 | H10: ='COMP DATA'!I10 -> 811.65 | I10: ='COMP DATA'!J10*10 -> 2432.6288 | J10: =H10*I10 -> 1974443.1 | K10: ='COMP DATA'!K10*10 -> 154138.33 | L10: ='COMP DATA'!L10*10 -> 96747.624 | M10: =J10+K10-L10 -> 2031833.9 | O10: ='COMP DATA'!M10*10 -> 544252.29 | P10: ='COMP DATA'!N10*10 -> 120814.27 | Q10: ='COMP DATA'!O10*10 -> 60656.785 | S10: =M10/O10 -> 3.7332574 | T10: =M10/P10 -> 16.817831 | U10: =J10/Q10 -> 32.551068
D11: Laurus Labs Limited | F11: ='COMP DATA'!H11 -> LAURUSLABS | H11: ='COMP DATA'!I11 -> 1493.3 | I11: ='COMP DATA'!J11*10 -> 5404.5959 | J11: =H11*I11 -> 8070683 | K11: ='COMP DATA'!K11*10 -> 256735.31 | L11: ='COMP DATA'!L11*10 -> 11590.643 | M11: =J11+K11-L11 -> 8315827.7 | O11: ='COMP DATA'!M11*10 -> 694510.97 | P11: ='COMP DATA'!N11*10 -> 181396.12 | Q11: ='COMP DATA'!O11*10 -> 90603.767 | S11: =M11/O11 -> 11.973645 | T11: =M11/P11 -> 45.84347 | U11: =J11/Q11 -> 89.076683
D13: Average | S13: =AVERAGE(S8:S11) -> 7.9254476 | T13: =AVERAGE(T8:T11) -> 31.214128 | U13: =AVERAGE(U8:U11) -> 55.891248
D14: Median | S14: =MEDIAN(S8:S11) -> 7.997444 | T14: =MEDIAN(T8:T11) -> 31.097605 | U14: =MEDIAN(U8:U11) -> 50.968621
D16: Acutaas Chemicals Limited | F16: ='COMP DATA'!H6 -> ACUTAAS | H16: ='COMP DATA'!I6 -> 3567.5 | I16: ='COMP DATA'!J6*10 -> 821.43255 | J16: =H16*I16 -> 2930460.6 | K16: ='COMP DATA'!K6*10 -> 3628.6664 | L16: ='COMP DATA'!L6*10 -> 22919.739 | M16: =J16+K16-L16 -> 2911169.5 | O16: ='COMP DATA'!M6*10 -> 136535.83 | P16: ='COMP DATA'!N6*10 -> 48973.906 | Q16: ='COMP DATA'!O6*10 -> 36316.871 | S16: =M16/O16 -> 21.321653 | T16: =M16/P16 -> 59.443279 | U16: =J16/Q16 -> 80.691439
D18: Metric | E18: Comps | H18: EV | I18: Net Debt | J18: Equity Value | K18: Shares | L18: Share Price
D19: EV/Revenue | E19: =S14 -> 7.997444 | H19: =E19*O16 -> 1091937.6 | I19: =K16-L16 -> -19291.072 | J19: =H19-I19 -> 1111228.7 | K19: =$I$16 -> 821.43255 | L19: =J19/K19 -> 1352.7936
D20: EV/EBITDA | E20: =T14 -> 31.097605 | H20: =E20*P16 -> 1522971.2 | I20: =I19 -> -19291.072 | J20: =H20-I20 -> 1542262.2 | K20: =$I$16 -> 821.43255 | L20: =J20/K20 -> 1877.5276
D21: P/E | E21: =U14 -> 50.968621 | H21: =+J21+I21 -> 1831729.8 | I21: =I20 -> -19291.072 | J21: =E21*Q16 -> 1851020.8 | K21: =$I$16 -> 821.43255 | L21: =J21/K21 -> 2253.4058

Sheet COMP DATA
A1: ACUTAAS CHEMICALS LIMITED
A2: COMPS DATA
D5: Company | H5: Ticker | I5: Price | J5: Shares (M) | K5: Debt (MM) | L5: Cash (MM) | M5: Sales (MM) | N5: EBITDA (MM) | O5: Net Income (MM) | P5: Tax %
D6: Acutaas Chemicals Limited | H6: ACUTAAS | I6: 3567.5 | J6: 82.143255 | K6: 362.86664 | L6: 2291.9739 | M6: 13653.583 | N6: 4897.3906 | O6: 3631.6871 | P6: 0.261756
D8: Neuland Laboratories Limited | H8: 524558 | I8: 18781.85 | J8: 12.829946 | K8: 3071.1862 | L8: 3618.5327 | M8: 20622.43 | N8: 5856.4638 | O8: 3710.6208 | P8: 0.255592
D9: Ipca Laboratories Limited | H9: IPCALAB | I9: 1696.4 | J9: 253.69497 | K9: 8244.5462 | L9: 12174.66 | M9: 98335.246 | N9: 20169.555 | O9: 11632.643 | P9: 0.243557
D10: Granules India Limited | H10: 532482 | I10: 811.65 | J10: 243.26288 | K10: 15413.833 | L10: 9674.7624 | M10: 54425.229 | N10: 12081.427 | O10: 6065.6785 | P10: 0.241993
D11: Laurus Labs Limited | H11: LAURUSLABS | I11: 1493.3 | J11: 540.45959 | K11: 25673.531 | L11: 1159.0643 | M11: 69451.097 | N11: 18139.612 | O11: 9060.3767 | P11: 0.247028
A15: Source: www.finchat.io | E15: 46205

Sheet MARKET DATA
A1: ACUTAAS CHEMICALS LIMITED
A2: EQUITY MARKET RETURN
B4: INDEX
A5: DATE | B5: CLOSE PRICE | D5: INDEX | E5: NIFTY50 TRI
A6: 46204 | B6: 36358.08
A7: 46203 | B7: 36145.88
A8: 46202 | B8: 36262.15 | D8: YEARFRAC | E8: =YEARFRAC(A6,A2482) -> 10
A9: 46198 | B9: 36428.37
A10: 46197 | B10: 36376.39
A11: 46196 | B11: 36077.17 | D11: MARKET RETURN | E11: =_xlfn.RRI(E8,B2482,B6) -> 0.125206
A12: 46195 | B12: 36489.39
A13: 46192 | B13: 36353.45
A14: 46191 | B14: 36519.02
A15: 46190 | B15: 36394.66
A16: 46189 | B16: 36248.81
A17: 46188 | B17: 36044.4
A18: 46185 | B18: 35695.33
A19: 46184 | B19: 34985.25
A20: 46183 | B20: 35065.85
A21: 46182 | B21: 35106.89
A22: 46181 | B22: 34926.96
A23: 46178 | B23: 35295.11
... A2482: 42552 | B2482: 11175.85

Sheet WACC
A1: ='HISTORICAL INFORMATION'!A1 -> ACUTAAS CHEMICALS LIMITED
A2: WEIGHTED-AVERAGE COST OF CAPITAL (WACC)
A3: ALL AMOUNTS DENOMINATED IN INR LAKHS
A6: COMPARABLE COMPANIES BETA
H8: Equity | I8: Total | J8: Debt/ | K8: Debt/ | L8: Tax | M8: Levered | N8: Unlevered
D9: Company Name | H9: Value | I9: Debt | J9: Equity | K9: Capital | L9: Rate % | M9: Beta | N9: Beta
D10: Neuland Laboratories Limited | H10: =COMP!J8 -> 2409701.2 | I10: =COMP!K8 -> 30711.862 | J10: =I10/H10 -> 0.012745091 | K10: =I10/(H10+I10) -> 0.012584698 | L10: ='COMP DATA'!P8 -> 0.255592 | M10: -0.32 | N10: =M10/(1+J10*(1-L10)) -> -0.31699252
D11: Ipca Laboratories Limited | H11: =COMP!J9 -> 4303681.6 | I11: =COMP!K9 -> 82445.462 | J11: =I11/H11 -> 0.019156962 | K11: =I11/(H11+I11) -> 0.018796871 | L11: ='COMP DATA'!P9 -> 0.243557 | M11: 0.04 | N11: =M11/(1+J11*(1-L11)) -> 0.039428634
D12: Granules India Limited | H12: =COMP!J10 -> 1974443.1 | I12: =COMP!K10 -> 154138.33 | J12: =I12/H12 -> 0.078066737 | K12: =I12/(H12+I12) -> 0.07241364 | L12: ='COMP DATA'!P10 -> 0.241993 | M12: 0.14 | N12: =M12/(1+J12*(1-L12)) -> 0.13217833
D13: Laurus Labs Limited | H13: =COMP!J11 -> 8070683 | I13: =COMP!K11 -> 256735.31 | J13: =I13/H13 -> 0.031810853 | K13: =I13/(H13+I13) -> 0.03083012 | L13: ='COMP DATA'!P11 -> 0.247028 | M13: 0.36 | N13: =M13/(1+J13*(1-L13)) -> 0.35157875
D14: AVERAGE | J14: =AVERAGE(J10:J13) -> 0.035444911 | K14: =AVERAGE(K10:K13) -> 0.033656332 | L14: =AVERAGE(L10:L13) -> 0.2470425 | M14: =AVERAGE(M10:M13) -> 0.055 | N14: =AVERAGE(N10:N13) -> 0.051548298
D15: MEDIAN | J15: =MEDIAN(J10:J13) -> 0.025483907 | K15: =MEDIAN(K10:K13) -> 0.024813495 | L15: =MEDIAN(L10:L13) -> 0.2452925 | M15: =MEDIAN(M10:M13) -> 0.09 | N15: =MEDIAN(N10:N13) -> 0.085803482
D17: Acutaas Chemicals Limited | H17: =COMP!J16 -> 2930460.6 | I17: =COMP!K16 -> 3628.6664
A20: WACC CALCULATION
C22: Target Capital Structure
D24: Proportion of Debt | H24: =K14 -> 0.033656332
D25: Proportion of Equity | H25: =1-H24 -> 0.96634367
C26: Current Capital Structure
D27: Market Cap | H27: =H17 -> 2930460.6
D28: Total Debt | H28: =I17 -> 3628.6664
D29: Debt/Equity | H29: =H28/H27 -> 0.001238258
C31: Cost of Debt
D32: Pre-Tax Cost Of Debt | H32: =MODEL!M13 -> 0.08
D33: Tax Rate | H33: =MODEL!E133 -> 0.261756
D34: After Cost of Debt | H34: =H32*(1-H33) -> 0.05905952
C36: Cost of Equity
D37: Risk Free Rate | H37: 0.067
D38: Equity Market Return | H38: ='MARKET DATA'!E11 -> 0.125206
D39: Equity Risk Premium | H39: =H38-H37 -> 0.058205996
D40: Levered Equity Beta | H40: =N15*(1+H29*(1-H33)) -> 0.085881918
D41: Cost Of Equity | H41: =H37+(H39*H40) -> 0.071998843
D43: WACC | H43: =(H34*H24)+(H41*H25) -> 0.071563352

Sheet BETA
A1: ACUTAAS CHEMICALS LIMITED
A2: HISTORICAL FINANCIAL INFORMATION
B4: INDEX | C4: % CHANGE | D4: STOCK | E4: % CHANGE
A5: DATE | B5: CLOSE PRICE | C5: MONTHLY | D5: CLOSE PRICE | E5: MONTHLY | G5: MIN | H5: =MIN(D52:D64) -> 1318.8
A6: 44440 | B6: 17618.15 | D6: 1282.5 | G6: MAX | H6: =MAX(D52:D64) -> 3546.4
A7: 44470 | B7: 17671.65 | C7: =B7/B6-1 -> 0.0030366412 | D7: 1025.05 | E7: =D7/D6-1 -> -0.20074074
A8: 44501 | B8: 16983.2 | C8: =B8/B7-1 -> -0.038957879 | D8: 901.85 | E8: =D8/D7-1 -> -0.12018926
A9: 44531 | B9: 17354.05 | C9: =B9/B8-1 -> 0.021836285 | D9: 1066.5 | E9: =D9/D8-1 -> 0.18256916 | G9: BETA | H9: =SLOPE(E7:E64,C7:C64) -> 0.23015038
A10: 44562 | B10: 17339.85 | C10: =B10/B9-1 -> -0.0008182528 | D10: 988.5 | E10: =D10/D9-1 -> -0.073136428
A11: 44593 | B11: 16793.9 | C11: =B11/B10-1 -> -0.031485278 | D11: 867.45 | E11: =D11/D10-1 -> -0.12245827
A12: 44621 | B12: 17464.75 | C12: =B12/B11-1 -> 0.039946052 | D12: 999.65 | E12: =D12/D11-1 -> 0.15240071
A13: 44652 | B13: 17102.55 | C13: =B13/B12-1 -> -0.020738917 | D13: 1134.85 | E13: =D13/D12-1 -> 0.13524734
A14: 44682 | B14: 16584.55 | C14: =B14/B13-1 -> -0.030287881 | D14: 871.45 | E14: =D14/D13-1 -> -0.23210116
A15: 44713 | B15: 15780.25 | C15: =B15/B14-1 -> -0.048496944 | D15: 876.65 | E15: =D15/D14-1 -> 0.0059670664
A16: 44743 | B16: 17158.25 | C16: =B16/B15-1 -> 0.087324345 | D16: 1038.4 | E16: =D16/D15-1 -> 0.18450921
A17: 44774 | B17: 17759.3 | C17: =B17/B16-1 -> 0.035029796 | D17: 992.65 | E17: =D17/D16-1 -> -0.044058166
A18: 44805 | B18: 17094.35 | C18: =B18/B17-1 -> -0.037442354 | D18: 912.65 | E18: =D18/D17-1 -> -0.080592354
A19: 44835 | B19: 18012.2 | C19: =B19/B18-1 -> 0.053693179 | D19: 947.65 | E19: =D19/D18-1 -> 0.03834986
A20: 44866 | B20: 18758.35 | C20: =B20/B19-1 -> 0.041424701 | D20: 974.1 | E20: =D20/D19-1 -> 0.027911149
A21: 44896 | B21: 18105.3 | C21: =B21/B20-1 -> -0.03481383 | D21: 965.45 | E21: =D21/D20-1 -> -0.0088799918
... A64: 46204 | B64: 24383.6 | C64: =B64/B63-1 -> 0.021698459 | D64: 3546.4 | E64: =D64/D63-1 -> 0.0058426456

Sheet SUMMARY
A1: ACUTAAS CHEMICALS LIMITED
A2: VALUATION SUMMARY- FOOTBALL FIELD
A4: Football Field Data
K5: Market
H6: Comps | I6: DCF | J6: 52 Week Hi/Lo | K6: Consensus
D7: High | H7: =MAX(COMP!L19:L21) -> 2253.4058 | I7: 1995.6442 | J7: =BETA!H6 -> 3546.4 | K7: 3970
D8: High | H8: =H7 -> 2253.4058 | I8: =I7 -> 1995.6442 | J8: =J7 -> 3546.4 | K8: =K7 -> 3970
D9: Low | H9: =MIN(COMP!L19:L21) -> 1352.7936 | I9: 1722.6944 | J9: =BETA!H5 -> 1318.8 | K9: 2890
D10: Low | H10: =H9 -> 1352.7936 | I10: =I9 -> 1722.6944 | J10: =J9 -> 1318.8 | K10: =K9 -> 2890
A12: Valuation Summary
